drawarrow/__init__.py
drawarrow/arrow_patch.py
drawarrow/arrow_spines.py
drawarrow/main.py
drawarrow/utils.py
drawarrow-0.1.0.dist-info/LICENSE
drawarrow-0.1.0.dist-info/METADATA
drawarrow-0.1.0.dist-info/WHEEL
drawarrow-0.1.0.dist-info/top_level.txt
drawarrow-0.1.0.dist-info/RECORD
