Metadata-Version: 2.2
Name: drawarrow
Version: 0.1.0
Summary: Drawing arrows for matplotlib made easy.
Home-page: https://github.com/JosephBARBIERDARNAL/drawarrow/
Author: Joseph Barbier
Author-email: Joseph Barbier <joseph.barbierdarnal@gmail.com>
Project-URL: Homepage, https://github.com/JosephBARBIERDARNAL/drawarrow
Project-URL: Issues, https://github.com/JosephBARBIERDARNAL/drawarrow/issues
Classifier: Programming Language :: Python :: 3
Classifier: License :: OSI Approved :: MIT License
Classifier: Operating System :: OS Independent
Classifier: Framework :: Matplotlib
Requires-Python: >=3.9
License-File: LICENSE
Requires-Dist: matplotlib
Dynamic: author
Dynamic: home-page
